intlib/__init__.py
intlib/exceptions.py
intlib/integroh_connector.py
intlib.py-0.0.2.dist-info/LICENSE
intlib.py-0.0.2.dist-info/METADATA
intlib.py-0.0.2.dist-info/WHEEL
intlib.py-0.0.2.dist-info/top_level.txt
intlib.py-0.0.2.dist-info/RECORD
