Metadata-Version: 2.1
Name: intlib.py
Version: 0.0.2
Summary: A small example package
Author-email: Marçal Junior <marssaljr@gmail.com>
Project-URL: Homepage, https://github.com/integroh/intlib.py
Project-URL: Issues, https://github.com/integroh/intlib.py/issues
Classifier: Programming Language :: Python :: 3
Classifier: License :: OSI Approved :: GNU General Public License v3 or later (GPLv3+)
Classifier: Operating System :: OS Independent
Classifier: Intended Audience :: Developers
Requires-Python: >=3.11.0
License-File: LICENSE
Requires-Dist: requests
